LICENSE
MANIFEST.in
README.md
setup.py
periscope_firehose/__init__.py
periscope_firehose/broadcast.py
periscope_firehose/constants.py
periscope_firehose/errors.py
periscope_firehose/firehose.py
periscope_firehose/utils.py
periscope_firehose.egg-info/PKG-INFO
periscope_firehose.egg-info/SOURCES.txt
periscope_firehose.egg-info/dependency_links.txt
periscope_firehose.egg-info/requires.txt
periscope_firehose.egg-info/top_level.txt