Metadata-Version: 1.0
Name: periscope-firehose
Version: 0.0.7
Summary: Listener for new public Periscope streams
Home-page: UNKNOWN
Author: Anastasis Germanidis
Author-email: agermanidis@gmail.com
License: The MIT License (MIT)
